{"height": 9, "width": 16, "pixels": [{"x": 0, "y": 0, "c": {"r": 0, "g": 0, "b": 0}}, {"x": 1, "y": 0, "c": {"r": 0, "g": 0, "b": 0}}, {"x": 2, "y": 0, "c": {"r": 0, "g": 0, "b": 0}}, {"x": 3, "y": 0, "c": {"r": 0, "g": 0, "b": 0}}, {"x": 4, "y": 0, "c": {"r": 0, "g": 0, "b": 0}}, {"x": 5, "y": 0, "c": {"r": 0, "g": 0, "b": 0}}, {"x": 6, "y": 0, "c": {"r": 0, "g": 0, "b": 0}}, {"x": 7, "y": 0, "c": {"r": 26, "g": 25, "b": 26}}, {"x": 8, "y": 0, "c": {"r": 228, "g": 227, "b": 228}}, {"x": 9, "y": 0, "c": {"r": 255, "g": 255, "b": 255}}, {"x": 10, "y": 0, "c": {"r": 255, "g": 253, "b": 255}}, {"x": 11, "y": 0, "c": {"r": 255, "g": 253, "b": 255}}, {"x": 12, "y": 0, "c": {"r": 255, "g": 253, "b": 255}}, {"x": 13, "y": 0, "c": {"r": 255, "g": 253, "b": 255}}, {"x": 14, "y": 0, "c": {"r": 255, "g": 253, "b": 255}}, {"x": 15, "y": 0, "c": {"r": 255, "g": 253, "b": 255}}, {"x": 0, "y": 1, "c": {"r": 0, "g": 0, "b": 0}}, {"x": 1, "y": 1, "c": {"r": 0, "g": 0, "b": 0}}, {"x": 2, "y": 1, "c": {"r": 0, "g": 0, "b": 0}}, {"x": 3, "y": 1, "c": {"r": 1, "g": 0, "b": 1}}, {"x": 4, "y": 1, "c": {"r": 0, "g": 0, "b": 0}}, {"x": 5, "y": 1, "c": {"r": 0, "g": 0, "b": 0}}, {"x": 6, "y": 1, "c": {"r": 0, "g": 0, "b": 0}}, {"x": 7, "y": 1, "c": {"r": 18, "g": 18, "b": 18}}, {"x": 8, "y": 1, "c": {"r": 235, "g": 234, "b": 235}}, {"x": 9, "y": 1, "c": {"r": 255, "g": 255, "b": 255}}, {"x": 10, "y": 1, "c": {"r": 255, "g": 253, "b": 255}}, {"x": 11, "y": 1, "c": {"r": 255, "g": 253, "b": 255}}, {"x": 12, "y": 1, "c": {"r": 255, "g": 253, "b": 255}}, {"x": 13, "y": 1, "c": {"r": 255, "g": 253, "b": 255}}, {"x": 14, "y": 1, "c": {"r": 255, "g": 253, "b": 255}}, {"x": 15, "y": 1, "c": {"r": 255, "g": 253, "b": 255}}, {"x": 0, "y": 2, "c": {"r": 0, "g": 0, "b": 0}}, {"x": 1, "y": 2, "c": {"r": 0, "g": 0, "b": 0}}, {"x": 2, "y": 2, "c": {"r": 0, "g": 0, "b": 0}}, {"x": 3, "y": 2, "c": {"r": 1, "g": 0, "b": 1}}, {"x": 4, "y": 2, "c": {"r": 0, "g": 0, "b": 0}}, {"x": 5, "y": 2, "c": {"r": 0, "g": 0, "b": 0}}, {"x": 6, "y": 2, "c": {"r": 38, "g": 37, "b": 38}}, {"x": 7, "y": 2, "c": {"r": 107, "g": 106, "b": 107}}, {"x": 8, "y": 2, "c": {"r": 139, "g": 138, "b": 139}}, {"x": 9, "y": 2, "c": {"r": 201, "g": 201, "b": 201}}, {"x": 10, "y": 2, "c": {"r": 255, "g": 254, "b": 255}}, {"x": 11, "y": 2, "c": {"r": 255, "g": 253, "b": 255}}, {"x": 12, "y": 2, "c": {"r": 255, "g": 253, "b": 255}}, {"x": 13, "y": 2, "c": {"r": 255, "g": 253, "b": 255}}, {"x": 14, "y": 2, "c": {"r": 255, "g": 253, "b": 255}}, {"x": 15, "y": 2, "c": {"r": 255, "g": 253, "b": 255}}, {"x": 0, "y": 3, "c": {"r": 0, "g": 0, "b": 0}}, {"x": 1, "y": 3, "c": {"r": 0, "g": 0, "b": 0}}, {"x": 2, "y": 3, "c": {"r": 0, "g": 0, "b": 0}}, {"x": 3, "y": 3, "c": {"r": 1, "g": 0, "b": 1}}, {"x": 4, "y": 3, "c": {"r": 0, "g": 0, "b": 0}}, {"x": 5, "y": 3, "c": {"r": 0, "g": 0, "b": 0}}, {"x": 6, "y": 3, "c": {"r": 142, "g": 141, "b": 142}}, {"x": 7, "y": 3, "c": {"r": 242, "g": 240, "b": 242}}, {"x": 8, "y": 3, "c": {"r": 14, "g": 14, "b": 14}}, {"x": 9, "y": 3, "c": {"r": 93, "g": 92, "b": 93}}, {"x": 10, "y": 3, "c": {"r": 254, "g": 254, "b": 254}}, {"x": 11, "y": 3, "c": {"r": 255, "g": 254, "b": 255}}, {"x": 12, "y": 3, "c": {"r": 255, "g": 253, "b": 255}}, {"x": 13, "y": 3, "c": {"r": 255, "g": 253, "b": 255}}, {"x": 14, "y": 3, "c": {"r": 255, "g": 253, "b": 255}}, {"x": 15, "y": 3, "c": {"r": 255, "g": 253, "b": 255}}, {"x": 0, "y": 4, "c": {"r": 0, "g": 0, "b": 0}}, {"x": 1, "y": 4, "c": {"r": 0, "g": 0, "b": 0}}, {"x": 2, "y": 4, "c": {"r": 1, "g": 0, "b": 1}}, {"x": 3, "y": 4, "c": {"r": 1, "g": 0, "b": 1}}, {"x": 4, "y": 4, "c": {"r": 0, "g": 0, "b": 0}}, {"x": 5, "y": 4, "c": {"r": 0, "g": 0, "b": 0}}, {"x": 6, "y": 4, "c": {"r": 88, "g": 87, "b": 88}}, {"x": 7, "y": 4, "c": {"r": 212, "g": 210, "b": 212}}, {"x": 8, "y": 4, "c": {"r": 35, "g": 34, "b": 35}}, {"x": 9, "y": 4, "c": {"r": 134, "g": 133, "b": 134}}, {"x": 10, "y": 4, "c": {"r": 254, "g": 252, "b": 254}}, {"x": 11, "y": 4, "c": {"r": 255, "g": 254, "b": 255}}, {"x": 12, "y": 4, "c": {"r": 255, "g": 253, "b": 255}}, {"x": 13, "y": 4, "c": {"r": 255, "g": 253, "b": 255}}, {"x": 14, "y": 4, "c": {"r": 255, "g": 253, "b": 255}}, {"x": 15, "y": 4, "c": {"r": 255, "g": 253, "b": 255}}, {"x": 0, "y": 5, "c": {"r": 0, "g": 0, "b": 0}}, {"x": 1, "y": 5, "c": {"r": 0, "g": 0, "b": 0}}, {"x": 2, "y": 5, "c": {"r": 0, "g": 0, "b": 0}}, {"x": 3, "y": 5, "c": {"r": 0, "g": 0, "b": 0}}, {"x": 4, "y": 5, "c": {"r": 0, "g": 0, "b": 0}}, {"x": 5, "y": 5, "c": {"r": 0, "g": 0, "b": 0}}, {"x": 6, "y": 5, "c": {"r": 115, "g": 114, "b": 115}}, {"x": 7, "y": 5, "c": {"r": 228, "g": 227, "b": 228}}, {"x": 8, "y": 5, "c": {"r": 25, "g": 25, "b": 25}}, {"x": 9, "y": 5, "c": {"r": 105, "g": 104, "b": 105}}, {"x": 10, "y": 5, "c": {"r": 252, "g": 252, "b": 252}}, {"x": 11, "y": 5, "c": {"r": 255, "g": 253, "b": 255}}, {"x": 12, "y": 5, "c": {"r": 255, "g": 253, "b": 255}}, {"x": 13, "y": 5, "c": {"r": 255, "g": 253, "b": 255}}, {"x": 14, "y": 5, "c": {"r": 255, "g": 253, "b": 255}}, {"x": 15, "y": 5, "c": {"r": 255, "g": 253, "b": 255}}, {"x": 0, "y": 6, "c": {"r": 0, "g": 0, "b": 0}}, {"x": 1, "y": 6, "c": {"r": 0, "g": 0, "b": 0}}, {"x": 2, "y": 6, "c": {"r": 0, "g": 0, "b": 0}}, {"x": 3, "y": 6, "c": {"r": 0, "g": 0, "b": 0}}, {"x": 4, "y": 6, "c": {"r": 0, "g": 0, "b": 0}}, {"x": 5, "y": 6, "c": {"r": 2, "g": 2, "b": 2}}, {"x": 6, "y": 6, "c": {"r": 189, "g": 188, "b": 189}}, {"x": 7, "y": 6, "c": {"r": 237, "g": 236, "b": 237}}, {"x": 8, "y": 6, "c": {"r": 20, "g": 19, "b": 20}}, {"x": 9, "y": 6, "c": {"r": 50, "g": 49, "b": 50}}, {"x": 10, "y": 6, "c": {"r": 246, "g": 245, "b": 246}}, {"x": 11, "y": 6, "c": {"r": 255, "g": 255, "b": 255}}, {"x": 12, "y": 6, "c": {"r": 255, "g": 253, "b": 255}}, {"x": 13, "y": 6, "c": {"r": 255, "g": 253, "b": 255}}, {"x": 14, "y": 6, "c": {"r": 255, "g": 253, "b": 255}}, {"x": 15, "y": 6, "c": {"r": 255, "g": 253, "b": 255}}, {"x": 0, "y": 7, "c": {"r": 0, "g": 0, "b": 0}}, {"x": 1, "y": 7, "c": {"r": 0, "g": 0, "b": 0}}, {"x": 2, "y": 7, "c": {"r": 0, "g": 0, "b": 0}}, {"x": 3, "y": 7, "c": {"r": 0, "g": 0, "b": 0}}, {"x": 4, "y": 7, "c": {"r": 0, "g": 0, "b": 0}}, {"x": 5, "y": 7, "c": {"r": 0, "g": 0, "b": 0}}, {"x": 6, "y": 7, "c": {"r": 145, "g": 144, "b": 145}}, {"x": 7, "y": 7, "c": {"r": 237, "g": 236, "b": 237}}, {"x": 8, "y": 7, "c": {"r": 17, "g": 17, "b": 17}}, {"x": 9, "y": 7, "c": {"r": 92, "g": 91, "b": 92}}, {"x": 10, "y": 7, "c": {"r": 255, "g": 255, "b": 255}}, {"x": 11, "y": 7, "c": {"r": 255, "g": 253, "b": 255}}, {"x": 12, "y": 7, "c": {"r": 255, "g": 253, "b": 255}}, {"x": 13, "y": 7, "c": {"r": 255, "g": 253, "b": 255}}, {"x": 14, "y": 7, "c": {"r": 255, "g": 253, "b": 255}}, {"x": 15, "y": 7, "c": {"r": 255, "g": 253, "b": 255}}, {"x": 0, "y": 8, "c": {"r": 0, "g": 0, "b": 0}}, {"x": 1, "y": 8, "c": {"r": 0, "g": 0, "b": 0}}, {"x": 2, "y": 8, "c": {"r": 0, "g": 0, "b": 0}}, {"x": 3, "y": 8, "c": {"r": 0, "g": 0, "b": 0}}, {"x": 4, "y": 8, "c": {"r": 0, "g": 0, "b": 0}}, {"x": 5, "y": 8, "c": {"r": 0, "g": 0, "b": 0}}, {"x": 6, "y": 8, "c": {"r": 171, "g": 169, "b": 171}}, {"x": 7, "y": 8, "c": {"r": 236, "g": 235, "b": 236}}, {"x": 8, "y": 8, "c": {"r": 20, "g": 20, "b": 20}}, {"x": 9, "y": 8, "c": {"r": 58, "g": 57, "b": 58}}, {"x": 10, "y": 8, "c": {"r": 247, "g": 246, "b": 247}}, {"x": 11, "y": 8, "c": {"r": 255, "g": 255, "b": 255}}, {"x": 12, "y": 8, "c": {"r": 255, "g": 253, "b": 255}}, {"x": 13, "y": 8, "c": {"r": 255, "g": 253, "b": 255}}, {"x": 14, "y": 8, "c": {"r": 255, "g": 253, "b": 255}}, {"x": 15, "y": 8, "c": {"r": 255, "g": 253, "b": 255}}]}