{"height": 9, "width": 16, "pixels": [{"x": 0, "y": 0, "c": {"r": 0, "g": 0, "b": 0}}, {"x": 1, "y": 0, "c": {"r": 0, "g": 0, "b": 0}}, {"x": 2, "y": 0, "c": {"r": 0, "g": 0, "b": 0}}, {"x": 3, "y": 0, "c": {"r": 0, "g": 0, "b": 0}}, {"x": 4, "y": 0, "c": {"r": 0, "g": 0, "b": 0}}, {"x": 5, "y": 0, "c": {"r": 0, "g": 0, "b": 0}}, {"x": 6, "y": 0, "c": {"r": 0, "g": 0, "b": 0}}, {"x": 7, "y": 0, "c": {"r": 0, "g": 0, "b": 0}}, {"x": 8, "y": 0, "c": {"r": 0, "g": 0, "b": 0}}, {"x": 9, "y": 0, "c": {"r": 0, "g": 0, "b": 0}}, {"x": 10, "y": 0, "c": {"r": 0, "g": 0, "b": 0}}, {"x": 11, "y": 0, "c": {"r": 0, "g": 0, "b": 0}}, {"x": 12, "y": 0, "c": {"r": 0, "g": 0, "b": 0}}, {"x": 13, "y": 0, "c": {"r": 0, "g": 0, "b": 0}}, {"x": 14, "y": 0, "c": {"r": 0, "g": 0, "b": 0}}, {"x": 15, "y": 0, "c": {"r": 0, "g": 0, "b": 0}}, {"x": 0, "y": 1, "c": {"r": 0, "g": 0, "b": 0}}, {"x": 1, "y": 1, "c": {"r": 0, "g": 0, "b": 0}}, {"x": 2, "y": 1, "c": {"r": 0, "g": 0, "b": 0}}, {"x": 3, "y": 1, "c": {"r": 1, "g": 0, "b": 1}}, {"x": 4, "y": 1, "c": {"r": 10, "g": 9, "b": 10}}, {"x": 5, "y": 1, "c": {"r": 3, "g": 3, "b": 3}}, {"x": 6, "y": 1, "c": {"r": 10, "g": 10, "b": 10}}, {"x": 7, "y": 1, "c": {"r": 19, "g": 19, "b": 19}}, {"x": 8, "y": 1, "c": {"r": 0, "g": 0, "b": 0}}, {"x": 9, "y": 1, "c": {"r": 0, "g": 0, "b": 0}}, {"x": 10, "y": 1, "c": {"r": 1, "g": 0, "b": 1}}, {"x": 11, "y": 1, "c": {"r": 0, "g": 0, "b": 0}}, {"x": 12, "y": 1, "c": {"r": 0, "g": 0, "b": 0}}, {"x": 13, "y": 1, "c": {"r": 1, "g": 0, "b": 1}}, {"x": 14, "y": 1, "c": {"r": 0, "g": 0, "b": 0}}, {"x": 15, "y": 1, "c": {"r": 0, "g": 0, "b": 0}}, {"x": 0, "y": 2, "c": {"r": 0, "g": 0, "b": 0}}, {"x": 1, "y": 2, "c": {"r": 0, "g": 0, "b": 0}}, {"x": 2, "y": 2, "c": {"r": 0, "g": 0, "b": 0}}, {"x": 3, "y": 2, "c": {"r": 0, "g": 0, "b": 0}}, {"x": 4, "y": 2, "c": {"r": 93, "g": 92, "b": 93}}, {"x": 5, "y": 2, "c": {"r": 189, "g": 188, "b": 189}}, {"x": 6, "y": 2, "c": {"r": 204, "g": 202, "b": 204}}, {"x": 7, "y": 2, "c": {"r": 225, "g": 225, "b": 225}}, {"x": 8, "y": 2, "c": {"r": 87, "g": 86, "b": 87}}, {"x": 9, "y": 2, "c": {"r": 0, "g": 0, "b": 0}}, {"x": 10, "y": 2, "c": {"r": 1, "g": 0, "b": 1}}, {"x": 11, "y": 2, "c": {"r": 0, "g": 0, "b": 0}}, {"x": 12, "y": 2, "c": {"r": 0, "g": 0, "b": 0}}, {"x": 13, "y": 2, "c": {"r": 0, "g": 0, "b": 0}}, {"x": 14, "y": 2, "c": {"r": 0, "g": 0, "b": 0}}, {"x": 15, "y": 2, "c": {"r": 0, "g": 0, "b": 0}}, {"x": 0, "y": 3, "c": {"r": 0, "g": 0, "b": 0}}, {"x": 1, "y": 3, "c": {"r": 0, "g": 0, "b": 0}}, {"x": 2, "y": 3, "c": {"r": 0, "g": 0, "b": 0}}, {"x": 3, "y": 3, "c": {"r": 0, "g": 0, "b": 0}}, {"x": 4, "y": 3, "c": {"r": 21, "g": 21, "b": 21}}, {"x": 5, "y": 3, "c": {"r": 215, "g": 214, "b": 215}}, {"x": 6, "y": 3, "c": {"r": 255, "g": 255, "b": 255}}, {"x": 7, "y": 3, "c": {"r": 255, "g": 254, "b": 255}}, {"x": 8, "y": 3, "c": {"r": 91, "g": 90, "b": 91}}, {"x": 9, "y": 3, "c": {"r": 0, "g": 0, "b": 0}}, {"x": 10, "y": 3, "c": {"r": 0, "g": 0, "b": 0}}, {"x": 11, "y": 3, "c": {"r": 0, "g": 0, "b": 0}}, {"x": 12, "y": 3, "c": {"r": 0, "g": 0, "b": 0}}, {"x": 13, "y": 3, "c": {"r": 0, "g": 0, "b": 0}}, {"x": 14, "y": 3, "c": {"r": 0, "g": 0, "b": 0}}, {"x": 15, "y": 3, "c": {"r": 0, "g": 0, "b": 0}}, {"x": 0, "y": 4, "c": {"r": 1, "g": 0, "b": 1}}, {"x": 1, "y": 4, "c": {"r": 0, "g": 0, "b": 0}}, {"x": 2, "y": 4, "c": {"r": 0, "g": 0, "b": 0}}, {"x": 3, "y": 4, "c": {"r": 0, "g": 0, "b": 0}}, {"x": 4, "y": 4, "c": {"r": 0, "g": 0, "b": 0}}, {"x": 5, "y": 4, "c": {"r": 141, "g": 140, "b": 141}}, {"x": 6, "y": 4, "c": {"r": 255, "g": 255, "b": 255}}, {"x": 7, "y": 4, "c": {"r": 249, "g": 248, "b": 249}}, {"x": 8, "y": 4, "c": {"r": 127, "g": 125, "b": 127}}, {"x": 9, "y": 4, "c": {"r": 8, "g": 8, "b": 8}}, {"x": 10, "y": 4, "c": {"r": 0, "g": 0, "b": 0}}, {"x": 11, "y": 4, "c": {"r": 0, "g": 0, "b": 0}}, {"x": 12, "y": 4, "c": {"r": 0, "g": 0, "b": 0}}, {"x": 13, "y": 4, "c": {"r": 0, "g": 0, "b": 0}}, {"x": 14, "y": 4, "c": {"r": 0, "g": 0, "b": 0}}, {"x": 15, "y": 4, "c": {"r": 0, "g": 0, "b": 0}}, {"x": 0, "y": 5, "c": {"r": 1, "g": 0, "b": 1}}, {"x": 1, "y": 5, "c": {"r": 0, "g": 0, "b": 0}}, {"x": 2, "y": 5, "c": {"r": 0, "g": 0, "b": 0}}, {"x": 3, "y": 5, "c": {"r": 0, "g": 0, "b": 0}}, {"x": 4, "y": 5, "c": {"r": 0, "g": 0, "b": 0}}, {"x": 5, "y": 5, "c": {"r": 149, "g": 148, "b": 149}}, {"x": 6, "y": 5, "c": {"r": 255, "g": 255, "b": 255}}, {"x": 7, "y": 5, "c": {"r": 255, "g": 255, "b": 255}}, {"x": 8, "y": 5, "c": {"r": 255, "g": 255, "b": 255}}, {"x": 9, "y": 5, "c": {"r": 66, "g": 65, "b": 66}}, {"x": 10, "y": 5, "c": {"r": 0, "g": 0, "b": 0}}, {"x": 11, "y": 5, "c": {"r": 0, "g": 0, "b": 0}}, {"x": 12, "y": 5, "c": {"r": 0, "g": 0, "b": 0}}, {"x": 13, "y": 5, "c": {"r": 0, "g": 0, "b": 0}}, {"x": 14, "y": 5, "c": {"r": 0, "g": 0, "b": 0}}, {"x": 15, "y": 5, "c": {"r": 0, "g": 0, "b": 0}}, {"x": 0, "y": 6, "c": {"r": 1, "g": 0, "b": 1}}, {"x": 1, "y": 6, "c": {"r": 0, "g": 0, "b": 0}}, {"x": 2, "y": 6, "c": {"r": 0, "g": 0, "b": 0}}, {"x": 3, "y": 6, "c": {"r": 0, "g": 0, "b": 0}}, {"x": 4, "y": 6, "c": {"r": 52, "g": 51, "b": 52}}, {"x": 5, "y": 6, "c": {"r": 237, "g": 236, "b": 237}}, {"x": 6, "y": 6, "c": {"r": 255, "g": 255, "b": 255}}, {"x": 7, "y": 6, "c": {"r": 254, "g": 253, "b": 254}}, {"x": 8, "y": 6, "c": {"r": 255, "g": 255, "b": 255}}, {"x": 9, "y": 6, "c": {"r": 179, "g": 178, "b": 179}}, {"x": 10, "y": 6, "c": {"r": 20, "g": 19, "b": 20}}, {"x": 11, "y": 6, "c": {"r": 0, "g": 0, "b": 0}}, {"x": 12, "y": 6, "c": {"r": 0, "g": 0, "b": 0}}, {"x": 13, "y": 6, "c": {"r": 0, "g": 0, "b": 0}}, {"x": 14, "y": 6, "c": {"r": 0, "g": 0, "b": 0}}, {"x": 15, "y": 6, "c": {"r": 0, "g": 0, "b": 0}}, {"x": 0, "y": 7, "c": {"r": 0, "g": 0, "b": 0}}, {"x": 1, "y": 7, "c": {"r": 0, "g": 0, "b": 0}}, {"x": 2, "y": 7, "c": {"r": 0, "g": 0, "b": 0}}, {"x": 3, "y": 7, "c": {"r": 46, "g": 45, "b": 46}}, {"x": 4, "y": 7, "c": {"r": 217, "g": 216, "b": 217}}, {"x": 5, "y": 7, "c": {"r": 254, "g": 253, "b": 254}}, {"x": 6, "y": 7, "c": {"r": 217, "g": 215, "b": 217}}, {"x": 7, "y": 7, "c": {"r": 248, "g": 247, "b": 248}}, {"x": 8, "y": 7, "c": {"r": 255, "g": 255, "b": 255}}, {"x": 9, "y": 7, "c": {"r": 223, "g": 221, "b": 223}}, {"x": 10, "y": 7, "c": {"r": 51, "g": 51, "b": 51}}, {"x": 11, "y": 7, "c": {"r": 0, "g": 0, "b": 0}}, {"x": 12, "y": 7, "c": {"r": 0, "g": 0, "b": 0}}, {"x": 13, "y": 7, "c": {"r": 0, "g": 0, "b": 0}}, {"x": 14, "y": 7, "c": {"r": 0, "g": 0, "b": 0}}, {"x": 15, "y": 7, "c": {"r": 0, "g": 0, "b": 0}}, {"x": 0, "y": 8, "c": {"r": 0, "g": 0, "b": 0}}, {"x": 1, "y": 8, "c": {"r": 0, "g": 0, "b": 0}}, {"x": 2, "y": 8, "c": {"r": 40, "g": 39, "b": 40}}, {"x": 3, "y": 8, "c": {"r": 215, "g": 214, "b": 215}}, {"x": 4, "y": 8, "c": {"r": 249, "g": 249, "b": 249}}, {"x": 5, "y": 8, "c": {"r": 96, "g": 95, "b": 96}}, {"x": 6, "y": 8, "c": {"r": 165, "g": 164, "b": 165}}, {"x": 7, "y": 8, "c": {"r": 255, "g": 255, "b": 255}}, {"x": 8, "y": 8, "c": {"r": 255, "g": 255, "b": 255}}, {"x": 9, "y": 8, "c": {"r": 179, "g": 178, "b": 179}}, {"x": 10, "y": 8, "c": {"r": 7, "g": 6, "b": 7}}, {"x": 11, "y": 8, "c": {"r": 0, "g": 0, "b": 0}}, {"x": 12, "y": 8, "c": {"r": 0, "g": 0, "b": 0}}, {"x": 13, "y": 8, "c": {"r": 0, "g": 0, "b": 0}}, {"x": 14, "y": 8, "c": {"r": 0, "g": 0, "b": 0}}, {"x": 15, "y": 8, "c": {"r": 0, "g": 0, "b": 0}}]}