{"height": 9, "width": 16, "pixels": [{"x": 0, "y": 0, "c": {"r": 0, "g": 0, "b": 0}}, {"x": 1, "y": 0, "c": {"r": 0, "g": 0, "b": 0}}, {"x": 2, "y": 0, "c": {"r": 0, "g": 0, "b": 0}}, {"x": 3, "y": 0, "c": {"r": 0, "g": 0, "b": 0}}, {"x": 4, "y": 0, "c": {"r": 0, "g": 0, "b": 0}}, {"x": 5, "y": 0, "c": {"r": 0, "g": 0, "b": 0}}, {"x": 6, "y": 0, "c": {"r": 0, "g": 0, "b": 0}}, {"x": 7, "y": 0, "c": {"r": 0, "g": 0, "b": 0}}, {"x": 8, "y": 0, "c": {"r": 0, "g": 0, "b": 0}}, {"x": 9, "y": 0, "c": {"r": 0, "g": 0, "b": 0}}, {"x": 10, "y": 0, "c": {"r": 0, "g": 0, "b": 0}}, {"x": 11, "y": 0, "c": {"r": 0, "g": 0, "b": 0}}, {"x": 12, "y": 0, "c": {"r": 0, "g": 0, "b": 0}}, {"x": 13, "y": 0, "c": {"r": 0, "g": 0, "b": 0}}, {"x": 14, "y": 0, "c": {"r": 0, "g": 0, "b": 0}}, {"x": 15, "y": 0, "c": {"r": 0, "g": 0, "b": 0}}, {"x": 0, "y": 1, "c": {"r": 0, "g": 0, "b": 0}}, {"x": 1, "y": 1, "c": {"r": 0, "g": 0, "b": 0}}, {"x": 2, "y": 1, "c": {"r": 0, "g": 0, "b": 0}}, {"x": 3, "y": 1, "c": {"r": 0, "g": 0, "b": 0}}, {"x": 4, "y": 1, "c": {"r": 0, "g": 0, "b": 0}}, {"x": 5, "y": 1, "c": {"r": 0, "g": 0, "b": 0}}, {"x": 6, "y": 1, "c": {"r": 0, "g": 0, "b": 0}}, {"x": 7, "y": 1, "c": {"r": 0, "g": 0, "b": 0}}, {"x": 8, "y": 1, "c": {"r": 0, "g": 0, "b": 0}}, {"x": 9, "y": 1, "c": {"r": 0, "g": 0, "b": 0}}, {"x": 10, "y": 1, "c": {"r": 0, "g": 0, "b": 0}}, {"x": 11, "y": 1, "c": {"r": 0, "g": 0, "b": 0}}, {"x": 12, "y": 1, "c": {"r": 0, "g": 0, "b": 0}}, {"x": 13, "y": 1, "c": {"r": 0, "g": 0, "b": 0}}, {"x": 14, "y": 1, "c": {"r": 0, "g": 0, "b": 0}}, {"x": 15, "y": 1, "c": {"r": 0, "g": 0, "b": 0}}, {"x": 0, "y": 2, "c": {"r": 0, "g": 0, "b": 0}}, {"x": 1, "y": 2, "c": {"r": 0, "g": 0, "b": 0}}, {"x": 2, "y": 2, "c": {"r": 0, "g": 0, "b": 0}}, {"x": 3, "y": 2, "c": {"r": 0, "g": 0, "b": 0}}, {"x": 4, "y": 2, "c": {"r": 0, "g": 0, "b": 0}}, {"x": 5, "y": 2, "c": {"r": 0, "g": 0, "b": 0}}, {"x": 6, "y": 2, "c": {"r": 43, "g": 42, "b": 43}}, {"x": 7, "y": 2, "c": {"r": 138, "g": 137, "b": 138}}, {"x": 8, "y": 2, "c": {"r": 113, "g": 112, "b": 113}}, {"x": 9, "y": 2, "c": {"r": 6, "g": 6, "b": 6}}, {"x": 10, "y": 2, "c": {"r": 0, "g": 0, "b": 0}}, {"x": 11, "y": 2, "c": {"r": 0, "g": 0, "b": 0}}, {"x": 12, "y": 2, "c": {"r": 0, "g": 0, "b": 0}}, {"x": 13, "y": 2, "c": {"r": 0, "g": 0, "b": 0}}, {"x": 14, "y": 2, "c": {"r": 0, "g": 0, "b": 0}}, {"x": 15, "y": 2, "c": {"r": 0, "g": 0, "b": 0}}, {"x": 0, "y": 3, "c": {"r": 0, "g": 0, "b": 0}}, {"x": 1, "y": 3, "c": {"r": 0, "g": 0, "b": 0}}, {"x": 2, "y": 3, "c": {"r": 0, "g": 0, "b": 0}}, {"x": 3, "y": 3, "c": {"r": 0, "g": 0, "b": 0}}, {"x": 4, "y": 3, "c": {"r": 0, "g": 0, "b": 0}}, {"x": 5, "y": 3, "c": {"r": 0, "g": 0, "b": 0}}, {"x": 6, "y": 3, "c": {"r": 90, "g": 90, "b": 90}}, {"x": 7, "y": 3, "c": {"r": 255, "g": 255, "b": 255}}, {"x": 8, "y": 3, "c": {"r": 245, "g": 243, "b": 245}}, {"x": 9, "y": 3, "c": {"r": 26, "g": 26, "b": 26}}, {"x": 10, "y": 3, "c": {"r": 0, "g": 0, "b": 0}}, {"x": 11, "y": 3, "c": {"r": 0, "g": 0, "b": 0}}, {"x": 12, "y": 3, "c": {"r": 0, "g": 0, "b": 0}}, {"x": 13, "y": 3, "c": {"r": 0, "g": 0, "b": 0}}, {"x": 14, "y": 3, "c": {"r": 0, "g": 0, "b": 0}}, {"x": 15, "y": 3, "c": {"r": 0, "g": 0, "b": 0}}, {"x": 0, "y": 4, "c": {"r": 0, "g": 0, "b": 0}}, {"x": 1, "y": 4, "c": {"r": 0, "g": 0, "b": 0}}, {"x": 2, "y": 4, "c": {"r": 0, "g": 0, "b": 0}}, {"x": 3, "y": 4, "c": {"r": 0, "g": 0, "b": 0}}, {"x": 4, "y": 4, "c": {"r": 12, "g": 12, "b": 12}}, {"x": 5, "y": 4, "c": {"r": 106, "g": 106, "b": 106}}, {"x": 6, "y": 4, "c": {"r": 171, "g": 171, "b": 171}}, {"x": 7, "y": 4, "c": {"r": 237, "g": 236, "b": 237}}, {"x": 8, "y": 4, "c": {"r": 227, "g": 226, "b": 227}}, {"x": 9, "y": 4, "c": {"r": 69, "g": 69, "b": 69}}, {"x": 10, "y": 4, "c": {"r": 0, "g": 0, "b": 0}}, {"x": 11, "y": 4, "c": {"r": 0, "g": 0, "b": 0}}, {"x": 12, "y": 4, "c": {"r": 0, "g": 0, "b": 0}}, {"x": 13, "y": 4, "c": {"r": 0, "g": 0, "b": 0}}, {"x": 14, "y": 4, "c": {"r": 0, "g": 0, "b": 0}}, {"x": 15, "y": 4, "c": {"r": 0, "g": 0, "b": 0}}, {"x": 0, "y": 5, "c": {"r": 0, "g": 0, "b": 0}}, {"x": 1, "y": 5, "c": {"r": 0, "g": 0, "b": 0}}, {"x": 2, "y": 5, "c": {"r": 0, "g": 0, "b": 0}}, {"x": 3, "y": 5, "c": {"r": 0, "g": 0, "b": 0}}, {"x": 4, "y": 5, "c": {"r": 12, "g": 12, "b": 12}}, {"x": 5, "y": 5, "c": {"r": 81, "g": 81, "b": 81}}, {"x": 6, "y": 5, "c": {"r": 128, "g": 128, "b": 128}}, {"x": 7, "y": 5, "c": {"r": 243, "g": 241, "b": 243}}, {"x": 8, "y": 5, "c": {"r": 255, "g": 255, "b": 255}}, {"x": 9, "y": 5, "c": {"r": 212, "g": 211, "b": 212}}, {"x": 10, "y": 5, "c": {"r": 16, "g": 16, "b": 16}}, {"x": 11, "y": 5, "c": {"r": 0, "g": 0, "b": 0}}, {"x": 12, "y": 5, "c": {"r": 0, "g": 0, "b": 0}}, {"x": 13, "y": 5, "c": {"r": 0, "g": 0, "b": 0}}, {"x": 14, "y": 5, "c": {"r": 0, "g": 0, "b": 0}}, {"x": 15, "y": 5, "c": {"r": 0, "g": 0, "b": 0}}, {"x": 0, "y": 6, "c": {"r": 0, "g": 0, "b": 0}}, {"x": 1, "y": 6, "c": {"r": 0, "g": 0, "b": 0}}, {"x": 2, "y": 6, "c": {"r": 0, "g": 0, "b": 0}}, {"x": 3, "y": 6, "c": {"r": 0, "g": 0, "b": 0}}, {"x": 4, "y": 6, "c": {"r": 0, "g": 0, "b": 0}}, {"x": 5, "y": 6, "c": {"r": 0, "g": 0, "b": 0}}, {"x": 6, "y": 6, "c": {"r": 112, "g": 112, "b": 112}}, {"x": 7, "y": 6, "c": {"r": 244, "g": 243, "b": 244}}, {"x": 8, "y": 6, "c": {"r": 255, "g": 255, "b": 255}}, {"x": 9, "y": 6, "c": {"r": 203, "g": 202, "b": 203}}, {"x": 10, "y": 6, "c": {"r": 17, "g": 17, "b": 17}}, {"x": 11, "y": 6, "c": {"r": 0, "g": 0, "b": 0}}, {"x": 12, "y": 6, "c": {"r": 0, "g": 0, "b": 0}}, {"x": 13, "y": 6, "c": {"r": 0, "g": 0, "b": 0}}, {"x": 14, "y": 6, "c": {"r": 0, "g": 0, "b": 0}}, {"x": 15, "y": 6, "c": {"r": 0, "g": 0, "b": 0}}, {"x": 0, "y": 7, "c": {"r": 0, "g": 0, "b": 0}}, {"x": 1, "y": 7, "c": {"r": 0, "g": 0, "b": 0}}, {"x": 2, "y": 7, "c": {"r": 0, "g": 0, "b": 0}}, {"x": 3, "y": 7, "c": {"r": 0, "g": 0, "b": 0}}, {"x": 4, "y": 7, "c": {"r": 0, "g": 0, "b": 0}}, {"x": 5, "y": 7, "c": {"r": 0, "g": 0, "b": 0}}, {"x": 6, "y": 7, "c": {"r": 141, "g": 141, "b": 141}}, {"x": 7, "y": 7, "c": {"r": 255, "g": 255, "b": 255}}, {"x": 8, "y": 7, "c": {"r": 254, "g": 253, "b": 254}}, {"x": 9, "y": 7, "c": {"r": 85, "g": 84, "b": 85}}, {"x": 10, "y": 7, "c": {"r": 0, "g": 0, "b": 0}}, {"x": 11, "y": 7, "c": {"r": 0, "g": 0, "b": 0}}, {"x": 12, "y": 7, "c": {"r": 0, "g": 0, "b": 0}}, {"x": 13, "y": 7, "c": {"r": 0, "g": 0, "b": 0}}, {"x": 14, "y": 7, "c": {"r": 0, "g": 0, "b": 0}}, {"x": 15, "y": 7, "c": {"r": 0, "g": 0, "b": 0}}, {"x": 0, "y": 8, "c": {"r": 0, "g": 0, "b": 0}}, {"x": 1, "y": 8, "c": {"r": 0, "g": 0, "b": 0}}, {"x": 2, "y": 8, "c": {"r": 0, "g": 0, "b": 0}}, {"x": 3, "y": 8, "c": {"r": 0, "g": 0, "b": 0}}, {"x": 4, "y": 8, "c": {"r": 0, "g": 0, "b": 0}}, {"x": 5, "y": 8, "c": {"r": 9, "g": 9, "b": 9}}, {"x": 6, "y": 8, "c": {"r": 201, "g": 200, "b": 201}}, {"x": 7, "y": 8, "c": {"r": 255, "g": 255, "b": 255}}, {"x": 8, "y": 8, "c": {"r": 255, "g": 255, "b": 255}}, {"x": 9, "y": 8, "c": {"r": 150, "g": 149, "b": 150}}, {"x": 10, "y": 8, "c": {"r": 2, "g": 2, "b": 2}}, {"x": 11, "y": 8, "c": {"r": 0, "g": 0, "b": 0}}, {"x": 12, "y": 8, "c": {"r": 0, "g": 0, "b": 0}}, {"x": 13, "y": 8, "c": {"r": 0, "g": 0, "b": 0}}, {"x": 14, "y": 8, "c": {"r": 0, "g": 0, "b": 0}}, {"x": 15, "y": 8, "c": {"r": 0, "g": 0, "b": 0}}]}